dtoolkit/__init__.py
dtoolkit/_typing.py
dtoolkit/_version.py
dtoolkit/accessor/__init__.py
dtoolkit/accessor/register.py
dtoolkit/accessor/dataframe/__init__.py
dtoolkit/accessor/dataframe/boolean.py
dtoolkit/accessor/dataframe/change_axis_type.py
dtoolkit/accessor/dataframe/cols.py
dtoolkit/accessor/dataframe/decompose.py
dtoolkit/accessor/dataframe/drop_inf.py
dtoolkit/accessor/dataframe/drop_not_duplicates.py
dtoolkit/accessor/dataframe/drop_or_not.py
dtoolkit/accessor/dataframe/dropna_index.py
dtoolkit/accessor/dataframe/equal.py
dtoolkit/accessor/dataframe/expand.py
dtoolkit/accessor/dataframe/fillna_regression.py
dtoolkit/accessor/dataframe/filter_in.py
dtoolkit/accessor/dataframe/groupby_index.py
dtoolkit/accessor/dataframe/repeat.py
dtoolkit/accessor/dataframe/set_unique_index.py
dtoolkit/accessor/dataframe/to_series.py
dtoolkit/accessor/dataframe/to_zh.py
dtoolkit/accessor/dataframe/top_n.py
dtoolkit/accessor/dataframe/values_to_dict.py
dtoolkit/accessor/dataframe/weighted_mean.py
dtoolkit/accessor/index/__init__.py
dtoolkit/accessor/index/len.py
dtoolkit/accessor/index/to_set.py
dtoolkit/accessor/series/__init__.py
dtoolkit/accessor/series/bin.py
dtoolkit/accessor/series/change_axis_type.py
dtoolkit/accessor/series/cols.py
dtoolkit/accessor/series/drop_inf.py
dtoolkit/accessor/series/drop_not_duplicates.py
dtoolkit/accessor/series/dropna_index.py
dtoolkit/accessor/series/equal.py
dtoolkit/accessor/series/error_report.py
dtoolkit/accessor/series/eval.py
dtoolkit/accessor/series/expand.py
dtoolkit/accessor/series/filter_in.py
dtoolkit/accessor/series/getattr.py
dtoolkit/accessor/series/groupby_index.py
dtoolkit/accessor/series/invert_or_not.py
dtoolkit/accessor/series/jenks_bin.py
dtoolkit/accessor/series/jenks_breaks.py
dtoolkit/accessor/series/len.py
dtoolkit/accessor/series/query.py
dtoolkit/accessor/series/set_unique_index.py
dtoolkit/accessor/series/swap_index_values.py
dtoolkit/accessor/series/textdistance.py
my_data_toolkit-0.0.22.dist-info/licenses/LICENSE
my_data_toolkit-0.0.22.dist-info/METADATA
my_data_toolkit-0.0.22.dist-info/WHEEL
my_data_toolkit-0.0.22.dist-info/top_level.txt
my_data_toolkit-0.0.22.dist-info/RECORD
