Metadata-Version: 2.4
Name: my-data-toolkit
Version: 0.0.22
Summary: Face the engineering of data preprocessing.
Author-email: "Zero <@Zeroto521>" <Zeroto521@gmail.com>
License-Expression: MIT
Project-URL: Documentation, https://my-data-toolkit.readthedocs.io
Project-URL: Repository, https://github.com/Zeroto521/my-data-toolkit
Project-URL: Changelog, https://my-data-toolkit.readthedocs.io/en/latest/changelog.html
Classifier: Development Status :: 3 - Alpha
Classifier: Intended Audience :: Developers
Classifier: Intended Audience :: Education
Classifier: Intended Audience :: Science/Research
Classifier: Operating System :: Microsoft :: Windows
Classifier: Operating System :: MacOS
Classifier: Operating System :: Unix
Classifier: Programming Language :: Python
Classifier: Programming Language :: Python :: 3
Classifier: Programming Language :: Python :: 3 :: Only
Classifier: Programming Language :: Python :: 3.10
Classifier: Programming Language :: Python :: 3.11
Classifier: Programming Language :: Python :: 3.12
Classifier: Programming Language :: Python :: 3.13
Classifier: Programming Language :: Python :: 3.14
Classifier: Topic :: Scientific/Engineering
Classifier: Topic :: Scientific/Engineering :: GIS
Classifier: Topic :: Scientific/Engineering :: Information Analysis
Requires-Python: >=3.10
License-File: LICENSE
Requires-Dist: pandas>=2.0.3
Provides-Extra: opt
Requires-Dist: scikit-learn>=1.7; extra == "opt"
Requires-Dist: packaging; extra == "opt"
Requires-Dist: geopandas>=1.1.0; extra == "opt"
Provides-Extra: test
Requires-Dist: pytest; extra == "test"
Requires-Dist: pytest-xdist; extra == "test"
Requires-Dist: pytest-cov; extra == "test"
Requires-Dist: pytest-doctestplus; extra == "test"
Requires-Dist: codecov; extra == "test"
Provides-Extra: doc
Requires-Dist: sphinx; extra == "doc"
Requires-Dist: pydata-sphinx-theme; extra == "doc"
Requires-Dist: sphinx-toggleprompt; extra == "doc"
Requires-Dist: myst-parser; extra == "doc"
Requires-Dist: numpydoc; extra == "doc"
Requires-Dist: ipython; extra == "doc"
Requires-Dist: ipykernel; extra == "doc"
Requires-Dist: nbsphinx; extra == "doc"
Provides-Extra: sdist
Requires-Dist: build; extra == "sdist"
Requires-Dist: twine; extra == "sdist"
Dynamic: license-file
